glitch_test/glitch_test_tb.v
`timescale 1 ns / 1 ps

// half adder with gate delays
module half_adder (
    input a,
    input b,
    
    output sum,
    output c_out
);

    // output logic (with delay)
    assign #1 sum = a ^ b;
    assign #1 c_out = a & b;
    
endmodule

module glitch_test_tb();

    // sim time: 10000 * 1 ns = 10000 ns
    localparam DURATION = 10000;

    wire            c_0;
    wire            c_1;
    wire            c_2;
    wire    [3:0]   out;
    
    reg             clk = 0;
    reg             rst = 0;
    reg     [3:0]   count;
    
    // generate clock signal: 1 / ((2 * 4.167) * 1 ns) = 119,990,400.77 Hz
    always begin
        #4.167
        clk = ~clk;
    end
    
    half_adder ha_0 (.a(1'b1), .b(count[0]), .sum(out[0]), .c_out(c_0));
    half_adder ha_1 (.a(c_0), .b(count[1]), .sum(out[1]), .c_out(c_1));
    half_adder ha_2 (.a(c_1), .b(count[2]), .sum(out[2]), .c_out(c_2));
    half_adder ha_3 (.a(c_2), .b(count[3]), .sum(out[3]), .c_out());
    
    // let the counter count
    always @ (posedge clk or posedge rst) 
	begin
        if (rst == 1'b1) 
		begin
            count = 0;
        end else 
		begin
            count <= out;
        end
    end
    
    // pulse reset line high at the beginning
    initial begin
        #10
        rst = 1;
        #1
        rst = 0;
    end
    
    initial 
	begin
        $dumpfile("glitch_test_tb.vcd");
        $dumpvars(0, glitch_test_tb);
        
        #(DURATION)
        
        $display("Done");
        $finish;
    end
    
endmodule

glitch_test/glitch_test_tb.vcd
$date
	Thu Feb  1 15:33:50 2024
$end
$version
	Icarus Verilog
$end
$timescale
	1ps
$end
$scope module glitch_test_tb $end
$var wire 4 ! out [3:0] $end
$var wire 1 " c_2 $end
$var wire 1 # c_1 $end
$var wire 1 $ c_0 $end
$var reg 1 % clk $end
$var reg 4 & count [3:0] $end
$var reg 1 ' rst $end
$scope module ha_0 $end
$var wire 1 ( a $end
$var wire 1 ) b $end
$var wire 1 $ c_out $end
$var wire 1 * sum $end
$upscope $end
$scope module ha_1 $end
$var wire 1 $ a $end
$var wire 1 + b $end
$var wire 1 # c_out $end
$var wire 1 , sum $end
$upscope $end
$scope module ha_2 $end
$var wire 1 # a $end
$var wire 1 - b $end
$var wire 1 " c_out $end
$var wire 1 . sum $end
$upscope $end
$scope module ha_3 $end
$var wire 1 " a $end
$var wire 1 / b $end
$var wire 1 0 c_out $end
$var wire 1 1 sum $end
$upscope $end
$upscope $end
$enddefinitions $end
#0
$dumpvars
x1
x0
x/
x.
x-
x,
x+
x*
x)
1(
0'
bx &
0%
x$
x#
x"
bx !
$end
#4167
1%
#8334
0%
#10000
0)
0+
0-
0/
b0 &
1'
#11000
bx1 !
1*
0$
0#
0"
00
0'
#12000
0,
0.
b1 !
01
#12501
1)
b1 &
1%
#13501
b0 !
0*
1$
#14501
b10 !
1,
#16668
0%
#20835
0)
1+
b10 &
1%
#21835
1*
0$
b1 !
0,
1#
#22835
1,
0#
b111 !
1.
#23835
b11 !
0.
#25002
0%
#29169
1)
b11 &
1%
#30169
b10 !
0*
1$
#31169
b0 !
0,
1#
#32169
b100 !
1.
#33336
0%
#37503
0)
0+
1-
b100 &
1%
#38503
1*
0$
1,
0#
b11 !
0.
1"
#39503
0,
1.
0"
b1101 !
11
#40503
b101 !
01
#41670
0%
#45837
1)
b101 &
1%
#46837
b100 !
0*
1$
#47837
b110 !
1,
#50004
0%
#54171
0)
1+
b110 &
1%
#55171
1*
0$
b101 !
0,
1#
#56171
1,
0#
b11 !
0.
1"
#57171
1.
0"
b1111 !
11
#58171
b111 !
01
#58338
0%
#62505
1)
b111 &
1%
#63505
b110 !
0*
1$
#64505
b100 !
0,
1#
#65505
b0 !
0.
1"
#66505
b1000 !
11
#66672
0%
#70839
0)
0+
0-
1/
b1000 &
1%
#71839
1*
0$
1,
0#
1.
0"
b111 !
01
10
#72839
0,
0.
b1001 !
11
00
#75006
0%
#79173
1)
b1001 &
1%
#80173
b1000 !
0*
1$
#81173
b1010 !
1,
#83340
0%
#87507
0)
1+
b1010 &
1%
#88507
1*
0$
b1001 !
0,
1#
#89507
1,
0#
b1111 !
1.
#90507
b1011 !
0.
#91674
0%
#95841
1)
b1011 &
1%
#96841
b1010 !
0*
1$
#97841
b1000 !
0,
1#
#98841
b1100 !
1.
#100008
0%
#104175
0)
0+
1-
b1100 &
1%
#105175
1*
0$
1,
0#
b1011 !
0.
1"
#106175
0,
1.
0"
b101 !
01
10
#107175
b1101 !
11
00
#108342
0%
#112509
1)
b1101 &
1%
#113509
b1100 !
0*
1$
#114509
b1110 !
1,
#116676
0%
#120843
0)
1+
b1110 &
1%
#121843
1*
0$
b1101 !
0,
1#
#122843
1,
0#
b1011 !
0.
1"
#123843
1.
0"
b111 !
01
10
#124843
b1111 !
11
00
#125010
0%
#129177
1)
b1111 &
1%
#130177
b1110 !
0*
1$
#131177
b1100 !
0,
1#
#132177
b1000 !
0.
1"
#133177
b0 !
01
10
#133344
0%
#137511
0)
0+
0-
0/
b0 &
1%
#138511
1*
0$
1,
0#
1.
0"
b1111 !
11
00
#139511
0,
0.
b1 !
01
#141678
0%
#145845
1)
b1 &
1%
#146845
b0 !
0*
1$
#147845
b10 !
1,
#150012
0%
#154179
0)
1+
b10 &
1%
#155179
1*
0$
b1 !
0,
1#
#156179
1,
0#
b111 !
1.
#157179
b11 !
0.
#158346
0%
#162513
1)
b11 &
1%
#163513
b10 !
0*
1$
#164513
b0 !
0,
1#
#165513
b100 !
1.
#166680
0%
#170847
0)
0+
1-
b100 &
1%
#171847
1*
0$
1,
0#
b11 !
0.
1"
#172847
0,
1.
0"
b1101 !
11
#173847
b101 !
01
#175014
0%
#179181
1)
b101 &
1%
#180181
b100 !
0*
1$
#181181
b110 !
1,
#183348
0%
#187515
0)
1+
b110 &
1%
#188515
1*
0$
b101 !
0,
1#
#189515
1,
0#
b11 !
0.
1"
#190515
1.
0"
b1111 !
11
#191515
b111 !
01
#191682
0%
#195849
1)
b111 &
1%
#196849
b110 !
0*
1$
#197849
b100 !
0,
1#
#198849
b0 !
0.
1"
#199849
b1000 !
11
#200016
0%
#204183
0)
0+
0-
1/
b1000 &
1%
#205183
1*
0$
1,
0#
1.
0"
b111 !
01
10
#206183
0,
0.
b1001 !
11
00
#208350
0%
#212517
1)
b1001 &
1%
#213517
b1000 !
0*
1$
#214517
b1010 !
1,
#216684
0%
#220851
0)
1+
b1010 &
1%
#221851
1*
0$
b1001 !
0,
1#
#222851
1,
0#
b1111 !
1.
#223851
b1011 !
0.
#225018
0%
#229185
1)
b1011 &
1%
#230185
b1010 !
0*
1$
#231185
b1000 !
0,
1#
#232185
b1100 !
1.
#233352
0%
#237519
0)
0+
1-
b1100 &
1%
#238519
1*
0$
1,
0#
b1011 !
0.
1"
#239519
0,
1.
0"
b101 !
01
10
#240519
b1101 !
11
00
#241686
0%
#245853
1)
b1101 &
1%
#246853
b1100 !
0*
1$
#247853
b1110 !
1,
#250020
0%
#254187
0)
1+
b1110 &
1%
#255187
1*
0$
b1101 !
0,
1#
#256187
1,
0#
b1011 !
0.
1"
#257187
1.
0"
b111 !
01
10
#258187
b1111 !
11
00
#258354
0%
#262521
1)
b1111 &
1%
#263521
b1110 !
0*
1$
#264521
b1100 !
0,
1#
#265521
b1000 !
0.
1"
#266521
b0 !
01
10
#266688
0%
#270855
0)
0+
0-
0/
b0 &
1%
#271855
1*
0$
1,
0#
1.
0"
b1111 !
11
00
#272855
0,
0.
b1 !
01
#275022
0%
#279189
1)
b1 &
1%
#280189
b0 !
0*
1$
#281189
b10 !
1,
#283356
0%
#287523
0)
1+
b10 &
1%
#288523
1*
0$
b1 !
0,
1#
#289523
1,
0#
b111 !
1.
#290523
b11 !
0.
#291690
0%
#295857
1)
b11 &
1%
#296857
b10 !
0*
1$
#297857
b0 !
0,
1#
#298857
b100 !
1.
#300024
0%
#304191
0)
0+
1-
b100 &
1%
#305191
1*
0$
1,
0#
b11 !
0.
1"
#306191
0,
1.
0"
b1101 !
11
#307191
b101 !
01
#308358
0%
#312525
1)
b101 &
1%
#313525
b100 !
0*
1$
#314525
b110 !
1,
#316692
0%
#320859
0)
1+
b110 &
1%
#321859
1*
0$
b101 !
0,
1#
#322859
1,
0#
b11 !
0.
1"
#323859
1.
0"
b1111 !
11
#324859
b111 !
01
#325026
0%
#329193
1)
b111 &
1%
#330193
b110 !
0*
1$
#331193
b100 !
0,
1#
#332193
b0 !
0.
1"
#333193
b1000 !
11
#333360
0%
#337527
0)
0+
0-
1/
b1000 &
1%
#338527
1*
0$
1,
0#
1.
0"
b111 !
01
10
#339527
0,
0.
b1001 !
11
00
#341694
0%
#345861
1)
b1001 &
1%
#346861
b1000 !
0*
1$
#347861
b1010 !
1,
#350028
0%
#354195
0)
1+
b1010 &
1%
#355195
1*
0$
b1001 !
0,
1#
#356195
1,
0#
b1111 !
1.
#357195
b1011 !
0.
#358362
0%
#362529
1)
b1011 &
1%
#363529
b1010 !
0*
1$
#364529
b1000 !
0,
1#
#365529
b1100 !
1.
#366696
0%
#370863
0)
0+
1-
b1100 &
1%
#371863
1*
0$
1,
0#
b1011 !
0.
1"
#372863
0,
1.
0"
b101 !
01
10
#373863
b1101 !
11
00
#375030
0%
#379197
1)
b1101 &
1%
#380197
b1100 !
0*
1$
#381197
b1110 !
1,
#383364
0%
#387531
0)
1+
b1110 &
1%
#388531
1*
0$
b1101 !
0,
1#
#389531
1,
0#
b1011 !
0.
1"
#390531
1.
0"
b111 !
01
10
#391531
b1111 !
11
00
#391698
0%
#395865
1)
b1111 &
1%
#396865
b1110 !
0*
1$
#397865
b1100 !
0,
1#
#398865
b1000 !
0.
1"
#399865
b0 !
01
10
#400032
0%
#404199
0)
0+
0-
0/
b0 &
1%
#405199
1*
0$
1,
0#
1.
0"
b1111 !
11
00
#406199
0,
0.
b1 !
01
#408366
0%
#412533
1)
b1 &
1%
#413533
b0 !
0*
1$
#414533
b10 !
1,
#416700
0%
#420867
0)
1+
b10 &
1%
#421867
1*
0$
b1 !
0,
1#
#422867
1,
0#
b111 !
1.
#423867
b11 !
0.
#425034
0%
#429201
1)
b11 &
1%
#430201
b10 !
0*
1$
#431201
b0 !
0,
1#
#432201
b100 !
1.
#433368
0%
#437535
0)
0+
1-
b100 &
1%
#438535
1*
0$
1,
0#
b11 !
0.
1"
#439535
0,
1.
0"
b1101 !
11
#440535
b101 !
01
#441702
0%
#445869
1)
b101 &
1%
#446869
b100 !
0*
1$
#447869
b110 !
1,
#450036
0%
#454203
0)
1+
b110 &
1%
#455203
1*
0$
b101 !
0,
1#
#456203
1,
0#
b11 !
0.
1"
#457203
1.
0"
b1111 !
11
#458203
b111 !
01
#458370
0%
#462537
1)
b111 &
1%
#463537
b110 !
0*
1$
#464537
b100 !
0,
1#
#465537
b0 !
0.
1"
#466537
b1000 !
11
#466704
0%
#470871
0)
0+
0-
1/
b1000 &
1%
#471871
1*
0$
1,
0#
1.
0"
b111 !
01
10
#472871
0,
0.
b1001 !
11
00
#475038
0%
#479205
1)
b1001 &
1%
#480205
b1000 !
0*
1$
#481205
b1010 !
1,
#483372
0%
#487539
0)
1+
b1010 &
1%
#488539
1*
0$
b1001 !
0,
1#
#489539
1,
0#
b1111 !
1.
#490539
b1011 !
0.
#491706
0%
#495873
1)
b1011 &
1%
#496873
b1010 !
0*
1$
#497873
b1000 !
0,
1#
#498873
b1100 !
1.
#500040
0%
#504207
0)
0+
1-
b1100 &
1%
#505207
1*
0$
1,
0#
b1011 !
0.
1"
#506207
0,
1.
0"
b101 !
01
10
#507207
b1101 !
11
00
#508374
0%
#512541
1)
b1101 &
1%
#513541
b1100 !
0*
1$
#514541
b1110 !
1,
#516708
0%
#520875
0)
1+
b1110 &
1%
#521875
1*
0$
b1101 !
0,
1#
#522875
1,
0#
b1011 !
0.
1"
#523875
1.
0"
b111 !
01
10
#524875
b1111 !
11
00
#525042
0%
#529209
1)
b1111 &
1%
#530209
b1110 !
0*
1$
#531209
b1100 !
0,
1#
#532209
b1000 !
0.
1"
#533209
b0 !
01
10
#533376
0%
#537543
0)
0+
0-
0/
b0 &
1%
#538543
1*
0$
1,
0#
1.
0"
b1111 !
11
00
#539543
0,
0.
b1 !
01
#541710
0%
#545877
1)
b1 &
1%
#546877
b0 !
0*
1$
#547877
b10 !
1,
#550044
0%
#554211
0)
1+
b10 &
1%
#555211
1*
0$
b1 !
0,
1#
#556211
1,
0#
b111 !
1.
#557211
b11 !
0.
#558378
0%
#562545
1)
b11 &
1%
#563545
b10 !
0*
1$
#564545
b0 !
0,
1#
#565545
b100 !
1.
#566712
0%
#570879
0)
0+
1-
b100 &
1%
#571879
1*
0$
1,
0#
b11 !
0.
1"
#572879
0,
1.
0"
b1101 !
11
#573879
b101 !
01
#575046
0%
#579213
1)
b101 &
1%
#580213
b100 !
0*
1$
#581213
b110 !
1,
#583380
0%
#587547
0)
1+
b110 &
1%
#588547
1*
0$
b101 !
0,
1#
#589547
1,
0#
b11 !
0.
1"
#590547
1.
0"
b1111 !
11
#591547
b111 !
01
#591714
0%
#595881
1)
b111 &
1%
#596881
b110 !
0*
1$
#597881
b100 !
0,
1#
#598881
b0 !
0.
1"
#599881
b1000 !
11
#600048
0%
#604215
0)
0+
0-
1/
b1000 &
1%
#605215
1*
0$
1,
0#
1.
0"
b111 !
01
10
#606215
0,
0.
b1001 !
11
00
#608382
0%
#612549
1)
b1001 &
1%
#613549
b1000 !
0*
1$
#614549
b1010 !
1,
#616716
0%
#620883
0)
1+
b1010 &
1%
#621883
1*
0$
b1001 !
0,
1#
#622883
1,
0#
b1111 !
1.
#623883
b1011 !
0.
#625050
0%
#629217
1)
b1011 &
1%
#630217
b1010 !
0*
1$
#631217
b1000 !
0,
1#
#632217
b1100 !
1.
#633384
0%
#637551
0)
0+
1-
b1100 &
1%
#638551
1*
0$
1,
0#
b1011 !
0.
1"
#639551
0,
1.
0"
b101 !
01
10
#640551
b1101 !
11
00
#641718
0%
#645885
1)
b1101 &
1%
#646885
b1100 !
0*
1$
#647885
b1110 !
1,
#650052
0%
#654219
0)
1+
b1110 &
1%
#655219
1*
0$
b1101 !
0,
1#
#656219
1,
0#
b1011 !
0.
1"
#657219
1.
0"
b111 !
01
10
#658219
b1111 !
11
00
#658386
0%
#662553
1)
b1111 &
1%
#663553
b1110 !
0*
1$
#664553
b1100 !
0,
1#
#665553
b1000 !
0.
1"
#666553
b0 !
01
10
#666720
0%
#670887
0)
0+
0-
0/
b0 &
1%
#671887
1*
0$
1,
0#
1.
0"
b1111 !
11
00
#672887
0,
0.
b1 !
01
#675054
0%
#679221
1)
b1 &
1%
#680221
b0 !
0*
1$
#681221
b10 !
1,
#683388
0%
#687555
0)
1+
b10 &
1%
#688555
1*
0$
b1 !
0,
1#
#689555
1,
0#
b111 !
1.
#690555
b11 !
0.
#691722
0%
#695889
1)
b11 &
1%
#696889
b10 !
0*
1$
#697889
b0 !
0,
1#
#698889
b100 !
1.
#700056
0%
#704223
0)
0+
1-
b100 &
1%
#705223
1*
0$
1,
0#
b11 !
0.
1"
#706223
0,
1.
0"
b1101 !
11
#707223
b101 !
01
#708390
0%
#712557
1)
b101 &
1%
#713557
b100 !
0*
1$
#714557
b110 !
1,
#716724
0%
#720891
0)
1+
b110 &
1%
#721891
1*
0$
b101 !
0,
1#
#722891
1,
0#
b11 !
0.
1"
#723891
1.
0"
b1111 !
11
#724891
b111 !
01
#725058
0%
#729225
1)
b111 &
1%
#730225
b110 !
0*
1$
#731225
b100 !
0,
1#
#732225
b0 !
0.
1"
#733225
b1000 !
11
#733392
0%
#737559
0)
0+
0-
1/
b1000 &
1%
#738559
1*
0$
1,
0#
1.
0"
b111 !
01
10
#739559
0,
0.
b1001 !
11
00
#741726
0%
#745893
1)
b1001 &
1%
#746893
b1000 !
0*
1$
#747893
b1010 !
1,
#750060
0%
#754227
0)
1+
b1010 &
1%
#755227
1*
0$
b1001 !
0,
1#
#756227
1,
0#
b1111 !
1.
#757227
b1011 !
0.
#758394
0%
#762561
1)
b1011 &
1%
#763561
b1010 !
0*
1$
#764561
b1000 !
0,
1#
#765561
b1100 !
1.
#766728
0%
#770895
0)
0+
1-
b1100 &
1%
#771895
1*
0$
1,
0#
b1011 !
0.
1"
#772895
0,
1.
0"
b101 !
01
10
#773895
b1101 !
11
00
#775062
0%
#779229
1)
b1101 &
1%
#780229
b1100 !
0*
1$
#781229
b1110 !
1,
#783396
0%
#787563
0)
1+
b1110 &
1%
#788563
1*
0$
b1101 !
0,
1#
#789563
1,
0#
b1011 !
0.
1"
#790563
1.
0"
b111 !
01
10
#791563
b1111 !
11
00
#791730
0%
#795897
1)
b1111 &
1%
#796897
b1110 !
0*
1$
#797897
b1100 !
0,
1#
#798897
b1000 !
0.
1"
#799897
b0 !
01
10
#800064
0%
#804231
0)
0+
0-
0/
b0 &
1%
#805231
1*
0$
1,
0#
1.
0"
b1111 !
11
00
#806231
0,
0.
b1 !
01
#808398
0%
#812565
1)
b1 &
1%
#813565
b0 !
0*
1$
#814565
b10 !
1,
#816732
0%
#820899
0)
1+
b10 &
1%
#821899
1*
0$
b1 !
0,
1#
#822899
1,
0#
b111 !
1.
#823899
b11 !
0.
#825066
0%
#829233
1)
b11 &
1%
#830233
b10 !
0*
1$
#831233
b0 !
0,
1#
#832233
b100 !
1.
#833400
0%
#837567
0)
0+
1-
b100 &
1%
#838567
1*
0$
1,
0#
b11 !
0.
1"
#839567
0,
1.
0"
b1101 !
11
#840567
b101 !
01
#841734
0%
#845901
1)
b101 &
1%
#846901
b100 !
0*
1$
#847901
b110 !
1,
#850068
0%
#854235
0)
1+
b110 &
1%
#855235
1*
0$
b101 !
0,
1#
#856235
1,
0#
b11 !
0.
1"
#857235
1.
0"
b1111 !
11
#858235
b111 !
01
#858402
0%
#862569
1)
b111 &
1%
#863569
b110 !
0*
1$
#864569
b100 !
0,
1#
#865569
b0 !
0.
1"
#866569
b1000 !
11
#866736
0%
#870903
0)
0+
0-
1/
b1000 &
1%
#871903
1*
0$
1,
0#
1.
0"
b111 !
01
10
#872903
0,
0.
b1001 !
11
00
#875070
0%
#879237
1)
b1001 &
1%
#880237
b1000 !
0*
1$
#881237
b1010 !
1,
#883404
0%
#887571
0)
1+
b1010 &
1%
#888571
1*
0$
b1001 !
0,
1#
#889571
1,
0#
b1111 !
1.
#890571
b1011 !
0.
#891738
0%
#895905
1)
b1011 &
1%
#896905
b1010 !
0*
1$
#897905
b1000 !
0,
1#
#898905
b1100 !
1.
#900072
0%
#904239
0)
0+
1-
b1100 &
1%
#905239
1*
0$
1,
0#
b1011 !
0.
1"
#906239
0,
1.
0"
b101 !
01
10
#907239
b1101 !
11
00
#908406
0%
#912573
1)
b1101 &
1%
#913573
b1100 !
0*
1$
#914573
b1110 !
1,
#916740
0%
#920907
0)
1+
b1110 &
1%
#921907
1*
0$
b1101 !
0,
1#
#922907
1,
0#
b1011 !
0.
1"
#923907
1.
0"
b111 !
01
10
#924907
b1111 !
11
00
#925074
0%
#929241
1)
b1111 &
1%
#930241
b1110 !
0*
1$
#931241
b1100 !
0,
1#
#932241
b1000 !
0.
1"
#933241
b0 !
01
10
#933408
0%
#937575
0)
0+
0-
0/
b0 &
1%
#938575
1*
0$
1,
0#
1.
0"
b1111 !
11
00
#939575
0,
0.
b1 !
01
#941742
0%
#945909
1)
b1 &
1%
#946909
b0 !
0*
1$
#947909
b10 !
1,
#950076
0%
#954243
0)
1+
b10 &
1%
#955243
1*
0$
b1 !
0,
1#
#956243
1,
0#
b111 !
1.
#957243
b11 !
0.
#958410
0%
#962577
1)
b11 &
1%
#963577
b10 !
0*
1$
#964577
b0 !
0,
1#
#965577
b100 !
1.
#966744
0%
#970911
0)
0+
1-
b100 &
1%
#971911
1*
0$
1,
0#
b11 !
0.
1"
#972911
0,
1.
0"
b1101 !
11
#973911
b101 !
01
#975078
0%
#979245
1)
b101 &
1%
#980245
b100 !
0*
1$
#981245
b110 !
1,
#983412
0%
#987579
0)
1+
b110 &
1%
#988579
1*
0$
b101 !
0,
1#
#989579
1,
0#
b11 !
0.
1"
#990579
1.
0"
b1111 !
11
#991579
b111 !
01
#991746
0%
#995913
1)
b111 &
1%
#996913
b110 !
0*
1$
#997913
b100 !
0,
1#
#998913
b0 !
0.
1"
#999913
b1000 !
11
#1000080
0%
#1004247
0)
0+
0-
1/
b1000 &
1%
#1005247
1*
0$
1,
0#
1.
0"
b111 !
01
10
#1006247
0,
0.
b1001 !
11
00
#1008414
0%
#1012581
1)
b1001 &
1%
#1013581
b1000 !
0*
1$
#1014581
b1010 !
1,
#1016748
0%
#1020915
0)
1+
b1010 &
1%
#1021915
1*
0$
b1001 !
0,
1#
#1022915
1,
0#
b1111 !
1.
#1023915
b1011 !
0.
#1025082
0%
#1029249
1)
b1011 &
1%
#1030249
b1010 !
0*
1$
#1031249
b1000 !
0,
1#
#1032249
b1100 !
1.
#1033416
0%
#1037583
0)
0+
1-
b1100 &
1%
#1038583
1*
0$
1,
0#
b1011 !
0.
1"
#1039583
0,
1.
0"
b101 !
01
10
#1040583
b1101 !
11
00
#1041750
0%
#1045917
1)
b1101 &
1%
#1046917
b1100 !
0*
1$
#1047917
b1110 !
1,
#1050084
0%
#1054251
0)
1+
b1110 &
1%
#1055251
1*
0$
b1101 !
0,
1#
#1056251
1,
0#
b1011 !
0.
1"
#1057251
1.
0"
b111 !
01
10
#1058251
b1111 !
11
00
#1058418
0%
#1062585
1)
b1111 &
1%
#1063585
b1110 !
0*
1$
#1064585
b1100 !
0,
1#
#1065585
b1000 !
0.
1"
#1066585
b0 !
01
10
#1066752
0%
#1070919
0)
0+
0-
0/
b0 &
1%
#1071919
1*
0$
1,
0#
1.
0"
b1111 !
11
00
#1072919
0,
0.
b1 !
01
#1075086
0%
#1079253
1)
b1 &
1%
#1080253
b0 !
0*
1$
#1081253
b10 !
1,
#1083420
0%
#1087587
0)
1+
b10 &
1%
#1088587
1*
0$
b1 !
0,
1#
#1089587
1,
0#
b111 !
1.
#1090587
b11 !
0.
#1091754
0%
#1095921
1)
b11 &
1%
#1096921
b10 !
0*
1$
#1097921
b0 !
0,
1#
#1098921
b100 !
1.
#1100088
0%
#1104255
0)
0+
1-
b100 &
1%
#1105255
1*
0$
1,
0#
b11 !
0.
1"
#1106255
0,
1.
0"
b1101 !
11
#1107255
b101 !
01
#1108422
0%
#1112589
1)
b101 &
1%
#1113589
b100 !
0*
1$
#1114589
b110 !
1,
#1116756
0%
#1120923
0)
1+
b110 &
1%
#1121923
1*
0$
b101 !
0,
1#
#1122923
1,
0#
b11 !
0.
1"
#1123923
1.
0"
b1111 !
11
#1124923
b111 !
01
#1125090
0%
#1129257
1)
b111 &
1%
#1130257
b110 !
0*
1$
#1131257
b100 !
0,
1#
#1132257
b0 !
0.
1"
#1133257
b1000 !
11
#1133424
0%
#1137591
0)
0+
0-
1/
b1000 &
1%
#1138591
1*
0$
1,
0#
1.
0"
b111 !
01
10
#1139591
0,
0.
b1001 !
11
00
#1141758
0%
#1145925
1)
b1001 &
1%
#1146925
b1000 !
0*
1$
#1147925
b1010 !
1,
#1150092
0%
#1154259
0)
1+
b1010 &
1%
#1155259
1*
0$
b1001 !
0,
1#
#1156259
1,
0#
b1111 !
1.
#1157259
b1011 !
0.
#1158426
0%
#1162593
1)
b1011 &
1%
#1163593
b1010 !
0*
1$
#1164593
b1000 !
0,
1#
#1165593
b1100 !
1.
#1166760
0%
#1170927
0)
0+
1-
b1100 &
1%
#1171927
1*
0$
1,
0#
b1011 !
0.
1"
#1172927
0,
1.
0"
b101 !
01
10
#1173927
b1101 !
11
00
#1175094
0%
#1179261
1)
b1101 &
1%
#1180261
b1100 !
0*
1$
#1181261
b1110 !
1,
#1183428
0%
#1187595
0)
1+
b1110 &
1%
#1188595
1*
0$
b1101 !
0,
1#
#1189595
1,
0#
b1011 !
0.
1"
#1190595
1.
0"
b111 !
01
10
#1191595
b1111 !
11
00
#1191762
0%
#1195929
1)
b1111 &
1%
#1196929
b1110 !
0*
1$
#1197929
b1100 !
0,
1#
#1198929
b1000 !
0.
1"
#1199929
b0 !
01
10
#1200096
0%
#1204263
0)
0+
0-
0/
b0 &
1%
#1205263
1*
0$
1,
0#
1.
0"
b1111 !
11
00
#1206263
0,
0.
b1 !
01
#1208430
0%
#1212597
1)
b1 &
1%
#1213597
b0 !
0*
1$
#1214597
b10 !
1,
#1216764
0%
#1220931
0)
1+
b10 &
1%
#1221931
1*
0$
b1 !
0,
1#
#1222931
1,
0#
b111 !
1.
#1223931
b11 !
0.
#1225098
0%
#1229265
1)
b11 &
1%
#1230265
b10 !
0*
1$
#1231265
b0 !
0,
1#
#1232265
b100 !
1.
#1233432
0%
#1237599
0)
0+
1-
b100 &
1%
#1238599
1*
0$
1,
0#
b11 !
0.
1"
#1239599
0,
1.
0"
b1101 !
11
#1240599
b101 !
01
#1241766
0%
#1245933
1)
b101 &
1%
#1246933
b100 !
0*
1$
#1247933
b110 !
1,
#1250100
0%
#1254267
0)
1+
b110 &
1%
#1255267
1*
0$
b101 !
0,
1#
#1256267
1,
0#
b11 !
0.
1"
#1257267
1.
0"
b1111 !
11
#1258267
b111 !
01
#1258434
0%
#1262601
1)
b111 &
1%
#1263601
b110 !
0*
1$
#1264601
b100 !
0,
1#
#1265601
b0 !
0.
1"
#1266601
b1000 !
11
#1266768
0%
#1270935
0)
0+
0-
1/
b1000 &
1%
#1271935
1*
0$
1,
0#
1.
0"
b111 !
01
10
#1272935
0,
0.
b1001 !
11
00
#1275102
0%
#1279269
1)
b1001 &
1%
#1280269
b1000 !
0*
1$
#1281269
b1010 !
1,
#1283436
0%
#1287603
0)
1+
b1010 &
1%
#1288603
1*
0$
b1001 !
0,
1#
#1289603
1,
0#
b1111 !
1.
#1290603
b1011 !
0.
#1291770
0%
#1295937
1)
b1011 &
1%
#1296937
b1010 !
0*
1$
#1297937
b1000 !
0,
1#
#1298937
b1100 !
1.
#1300104
0%
#1304271
0)
0+
1-
b1100 &
1%
#1305271
1*
0$
1,
0#
b1011 !
0.
1"
#1306271
0,
1.
0"
b101 !
01
10
#1307271
b1101 !
11
00
#1308438
0%
#1312605
1)
b1101 &
1%
#1313605
b1100 !
0*
1$
#1314605
b1110 !
1,
#1316772
0%
#1320939
0)
1+
b1110 &
1%
#1321939
1*
0$
b1101 !
0,
1#
#1322939
1,
0#
b1011 !
0.
1"
#1323939
1.
0"
b111 !
01
10
#1324939
b1111 !
11
00
#1325106
0%
#1329273
1)
b1111 &
1%
#1330273
b1110 !
0*
1$
#1331273
b1100 !
0,
1#
#1332273
b1000 !
0.
1"
#1333273
b0 !
01
10
#1333440
0%
#1337607
0)
0+
0-
0/
b0 &
1%
#1338607
1*
0$
1,
0#
1.
0"
b1111 !
11
00
#1339607
0,
0.
b1 !
01
#1341774
0%
#1345941
1)
b1 &
1%
#1346941
b0 !
0*
1$
#1347941
b10 !
1,
#1350108
0%
#1354275
0)
1+
b10 &
1%
#1355275
1*
0$
b1 !
0,
1#
#1356275
1,
0#
b111 !
1.
#1357275
b11 !
0.
#1358442
0%
#1362609
1)
b11 &
1%
#1363609
b10 !
0*
1$
#1364609
b0 !
0,
1#
#1365609
b100 !
1.
#1366776
0%
#1370943
0)
0+
1-
b100 &
1%
#1371943
1*
0$
1,
0#
b11 !
0.
1"
#1372943
0,
1.
0"
b1101 !
11
#1373943
b101 !
01
#1375110
0%
#1379277
1)
b101 &
1%
#1380277
b100 !
0*
1$
#1381277
b110 !
1,
#1383444
0%
#1387611
0)
1+
b110 &
1%
#1388611
1*
0$
b101 !
0,
1#
#1389611
1,
0#
b11 !
0.
1"
#1390611
1.
0"
b1111 !
11
#1391611
b111 !
01
#1391778
0%
#1395945
1)
b111 &
1%
#1396945
b110 !
0*
1$
#1397945
b100 !
0,
1#
#1398945
b0 !
0.
1"
#1399945
b1000 !
11
#1400112
0%
#1404279
0)
0+
0-
1/
b1000 &
1%
#1405279
1*
0$
1,
0#
1.
0"
b111 !
01
10
#1406279
0,
0.
b1001 !
11
00
#1408446
0%
#1412613
1)
b1001 &
1%
#1413613
b1000 !
0*
1$
#1414613
b1010 !
1,
#1416780
0%
#1420947
0)
1+
b1010 &
1%
#1421947
1*
0$
b1001 !
0,
1#
#1422947
1,
0#
b1111 !
1.
#1423947
b1011 !
0.
#1425114
0%
#1429281
1)
b1011 &
1%
#1430281
b1010 !
0*
1$
#1431281
b1000 !
0,
1#
#1432281
b1100 !
1.
#1433448
0%
#1437615
0)
0+
1-
b1100 &
1%
#1438615
1*
0$
1,
0#
b1011 !
0.
1"
#1439615
0,
1.
0"
b101 !
01
10
#1440615
b1101 !
11
00
#1441782
0%
#1445949
1)
b1101 &
1%
#1446949
b1100 !
0*
1$
#1447949
b1110 !
1,
#1450116
0%
#1454283
0)
1+
b1110 &
1%
#1455283
1*
0$
b1101 !
0,
1#
#1456283
1,
0#
b1011 !
0.
1"
#1457283
1.
0"
b111 !
01
10
#1458283
b1111 !
11
00
#1458450
0%
#1462617
1)
b1111 &
1%
#1463617
b1110 !
0*
1$
#1464617
b1100 !
0,
1#
#1465617
b1000 !
0.
1"
#1466617
b0 !
01
10
#1466784
0%
#1470951
0)
0+
0-
0/
b0 &
1%
#1471951
1*
0$
1,
0#
1.
0"
b1111 !
11
00
#1472951
0,
0.
b1 !
01
#1475118
0%
#1479285
1)
b1 &
1%
#1480285
b0 !
0*
1$
#1481285
b10 !
1,
#1483452
0%
#1487619
0)
1+
b10 &
1%
#1488619
1*
0$
b1 !
0,
1#
#1489619
1,
0#
b111 !
1.
#1490619
b11 !
0.
#1491786
0%
#1495953
1)
b11 &
1%
#1496953
b10 !
0*
1$
#1497953
b0 !
0,
1#
#1498953
b100 !
1.
#1500120
0%
