no_glitch_counter/no_glitch_tb.v
`timescale 1 ns / 1 ps

module counter (
    input clk,
    input rst,
    
    output reg[3:0] count
);

    always @ (posedge clk or posedge rst) 
	begin
        if (rst == 1'b1) 
		begin
            count <= 0;
        end else 
		begin
            case (count)                            // state
                4'b0000:    #1 count <= 4'b0001;    // 0
                4'b0001:    #1 count <= 4'b0011;    // 1
                4'b0011:    #1 count <= 4'b0010;    // 2
                4'b0010:    #1 count <= 4'b0110;    // 3
                4'b0110:    #1 count <= 4'b0111;    // 4
                4'b0111:    #1 count <= 4'b0101;    // 5
                4'b0101:    #1 count <= 4'b0100;    // 6
                4'b0100:    #1 count <= 4'b1100;    // 7
                4'b1100:    #1 count <= 4'b1101;    // 8
                4'b1101:    #1 count <= 4'b1111;    // 9
                4'b1111:    #1 count <= 4'b1110;    // 10
                4'b1110:    #1 count <= 4'b1010;    // 11
                4'b1010:    #1 count <= 4'b1011;    // 12
                4'b1011:    #1 count <= 4'b1001;    // 13
                4'b1001:    #1 count <= 4'b1000;    // 14
                4'b1000:    #1 count <= 4'b0000;    // 15
                default:    #1 count <= 4'b0000;
            endcase
        end
    end
    
endmodule

module no_glitch_tb();
    localparam DURATION = 10000;

    wire[3:0] out;
    
    reg clk = 0;
    reg rst = 0;
    
    always begin
        #4.167
        clk = ~clk;
    end
    
    counter c1 (.clk(clk), .rst(rst), .count(out));
    
    // pulse reset line high at the beginning
    initial begin
        #10
        rst = 1;
        #1
        rst = 0;
    end
    
    initial begin
        $dumpfile("no_glitch_tb.vcd");
        $dumpvars(0, no_glitch_tb);
        
        #(DURATION)
        
        $display("Done");
        $finish;
    end
    
endmodule

no_glitch_counter/no_glitch_tb.vcd
$date
	Thu Feb  1 15:45:57 2024
$end
$version
	Icarus Verilog
$end
$timescale
	1ps
$end
$scope module no_glitch_tb $end
$var wire 4 ! out [3:0] $end
$var reg 1 " clk $end
$var reg 1 # rst $end
$scope module c1 $end
$var wire 1 " clk $end
$var wire 1 # rst $end
$var reg 4 $ count [3:0] $end
$upscope $end
$upscope $end
$enddefinitions $end
#0
$dumpvars
bx $
0#
0"
bx !
$end
#4167
1"
#5167
b0 !
b0 $
#8334
0"
#10000
1#
#11000
0#
#12501
1"
#13501
b1 !
b1 $
#16668
0"
#20835
1"
#21835
b11 !
b11 $
#25002
0"
#29169
1"
#30169
b10 !
b10 $
#33336
0"
#37503
1"
#38503
b110 !
b110 $
#41670
0"
#45837
1"
#46837
b111 !
b111 $
#50004
0"
#54171
1"
#55171
b101 !
b101 $
#58338
0"
#62505
1"
#63505
b100 !
b100 $
#66672
0"
#70839
1"
#71839
b1100 !
b1100 $
#75006
0"
#79173
1"
#80173
b1101 !
b1101 $
#83340
0"
#87507
1"
#88507
b1111 !
b1111 $
#91674
0"
#95841
1"
#96841
b1110 !
b1110 $
#100008
0"
#104175
1"
#105175
b1010 !
b1010 $
#108342
0"
#112509
1"
#113509
b1011 !
b1011 $
#116676
0"
#120843
1"
#121843
b1001 !
b1001 $
#125010
0"
#129177
1"
#130177
b1000 !
b1000 $
#133344
0"
#137511
1"
#138511
b0 !
b0 $
#141678
0"
#145845
1"
#146845
b1 !
b1 $
#150012
0"
#154179
1"
#155179
b11 !
b11 $
#158346
0"
#162513
1"
#163513
b10 !
b10 $
#166680
0"
#170847
1"
#171847
b110 !
b110 $
#175014
0"
#179181
1"
#180181
b111 !
b111 $
#183348
0"
#187515
1"
#188515
b101 !
b101 $
#191682
0"
#195849
1"
#196849
b100 !
b100 $
#200016
0"
#204183
1"
#205183
b1100 !
b1100 $
#208350
0"
#212517
1"
#213517
b1101 !
b1101 $
#216684
0"
#220851
1"
#221851
b1111 !
b1111 $
#225018
0"
#229185
1"
#230185
b1110 !
b1110 $
#233352
0"
#237519
1"
#238519
b1010 !
b1010 $
#241686
0"
#245853
1"
#246853
b1011 !
b1011 $
#250020
0"
#254187
1"
#255187
b1001 !
b1001 $
#258354
0"
#262521
1"
#263521
b1000 !
b1000 $
#266688
0"
#270855
1"
#271855
b0 !
b0 $
#275022
0"
#279189
1"
#280189
b1 !
b1 $
#283356
0"
#287523
1"
#288523
b11 !
b11 $
#291690
0"
#295857
1"
#296857
b10 !
b10 $
#300024
0"
#304191
1"
#305191
b110 !
b110 $
#308358
0"
#312525
1"
#313525
b111 !
b111 $
#316692
0"
#320859
1"
#321859
b101 !
b101 $
#325026
0"
#329193
1"
#330193
b100 !
b100 $
#333360
0"
#337527
1"
#338527
b1100 !
b1100 $
#341694
0"
#345861
1"
#346861
b1101 !
b1101 $
#350028
0"
#354195
1"
#355195
b1111 !
b1111 $
#358362
0"
#362529
1"
#363529
b1110 !
b1110 $
#366696
0"
#370863
1"
#371863
b1010 !
b1010 $
#375030
0"
#379197
1"
#380197
b1011 !
b1011 $
#383364
0"
#387531
1"
#388531
b1001 !
b1001 $
#391698
0"
#395865
1"
#396865
b1000 !
b1000 $
#400032
0"
#404199
1"
#405199
b0 !
b0 $
#408366
0"
#412533
1"
#413533
b1 !
b1 $
#416700
0"
#420867
1"
#421867
b11 !
b11 $
#425034
0"
#429201
1"
#430201
b10 !
b10 $
#433368
0"
#437535
1"
#438535
b110 !
b110 $
#441702
0"
#445869
1"
#446869
b111 !
b111 $
#450036
0"
#454203
1"
#455203
b101 !
b101 $
#458370
0"
#462537
1"
#463537
b100 !
b100 $
#466704
0"
#470871
1"
#471871
b1100 !
b1100 $
#475038
0"
#479205
1"
#480205
b1101 !
b1101 $
#483372
0"
#487539
1"
#488539
b1111 !
b1111 $
#491706
0"
#495873
1"
#496873
b1110 !
b1110 $
#500040
0"
#504207
1"
#505207
b1010 !
b1010 $
#508374
0"
#512541
1"
#513541
b1011 !
b1011 $
#516708
0"
#520875
1"
#521875
b1001 !
b1001 $
#525042
0"
#529209
1"
#530209
b1000 !
b1000 $
#533376
0"
#537543
1"
#538543
b0 !
b0 $
#541710
0"
#545877
1"
#546877
b1 !
b1 $
#550044
0"
#554211
1"
#555211
b11 !
b11 $
#558378
0"
#562545
1"
#563545
b10 !
b10 $
#566712
0"
#570879
1"
#571879
b110 !
b110 $
#575046
0"
#579213
1"
#580213
b111 !
b111 $
#583380
0"
#587547
1"
#588547
b101 !
b101 $
#591714
0"
#595881
1"
#596881
b100 !
b100 $
#600048
0"
#604215
1"
#605215
b1100 !
b1100 $
#608382
0"
#612549
1"
#613549
b1101 !
b1101 $
#616716
0"
#620883
1"
#621883
b1111 !
b1111 $
#625050
0"
#629217
1"
#630217
b1110 !
b1110 $
#633384
0"
#637551
1"
#638551
b1010 !
b1010 $
#641718
0"
#645885
1"
#646885
b1011 !
b1011 $
#650052
0"
#654219
1"
#655219
b1001 !
b1001 $
#658386
0"
#662553
1"
#663553
b1000 !
b1000 $
#666720
0"
#670887
1"
#671887
b0 !
b0 $
#675054
0"
#679221
1"
#680221
b1 !
b1 $
#683388
0"
#687555
1"
#688555
b11 !
b11 $
#691722
0"
#695889
1"
#696889
b10 !
b10 $
#700056
0"
#704223
1"
#705223
b110 !
b110 $
#708390
0"
#712557
1"
#713557
b111 !
b111 $
#716724
0"
#720891
1"
#721891
b101 !
b101 $
#725058
0"
#729225
1"
#730225
b100 !
b100 $
#733392
0"
#737559
1"
#738559
b1100 !
b1100 $
#741726
0"
#745893
1"
#746893
b1101 !
b1101 $
#750060
0"
#754227
1"
#755227
b1111 !
b1111 $
#758394
0"
#762561
1"
#763561
b1110 !
b1110 $
#766728
0"
#770895
1"
#771895
b1010 !
b1010 $
#775062
0"
#779229
1"
#780229
b1011 !
b1011 $
#783396
0"
#787563
1"
#788563
b1001 !
b1001 $
#791730
0"
#795897
1"
#796897
b1000 !
b1000 $
#800064
0"
#804231
1"
#805231
b0 !
b0 $
#808398
0"
#812565
1"
#813565
b1 !
b1 $
#816732
0"
#820899
1"
#821899
b11 !
b11 $
#825066
0"
#829233
1"
#830233
b10 !
b10 $
#833400
0"
#837567
1"
#838567
b110 !
b110 $
#841734
0"
#845901
1"
#846901
b111 !
b111 $
#850068
0"
#854235
1"
#855235
b101 !
b101 $
#858402
0"
#862569
1"
#863569
b100 !
b100 $
#866736
0"
#870903
1"
#871903
b1100 !
b1100 $
#875070
0"
#879237
1"
#880237
b1101 !
b1101 $
#883404
0"
#887571
1"
#888571
b1111 !
b1111 $
#891738
0"
#895905
1"
#896905
b1110 !
b1110 $
#900072
0"
#904239
1"
#905239
b1010 !
b1010 $
#908406
0"
#912573
1"
#913573
b1011 !
b1011 $
#916740
0"
#920907
1"
#921907
b1001 !
b1001 $
#925074
0"
#929241
1"
#930241
b1000 !
b1000 $
#933408
0"
#937575
1"
#938575
b0 !
b0 $
#941742
0"
#945909
1"
#946909
b1 !
b1 $
#950076
0"
#954243
1"
#955243
b11 !
b11 $
#958410
0"
#962577
1"
#963577
b10 !
b10 $
#966744
0"
#970911
1"
#971911
b110 !
b110 $
#975078
0"
#979245
1"
#980245
b111 !
b111 $
#983412
0"
#987579
1"
#988579
b101 !
b101 $
#991746
0"
#995913
1"
#996913
b100 !
b100 $
#1000080
0"
#1004247
1"
#1005247
b1100 !
b1100 $
#1008414
0"
#1012581
1"
#1013581
b1101 !
b1101 $
#1016748
0"
#1020915
1"
#1021915
b1111 !
b1111 $
#1025082
0"
#1029249
1"
#1030249
b1110 !
b1110 $
#1033416
0"
#1037583
1"
#1038583
b1010 !
b1010 $
#1041750
0"
#1045917
1"
#1046917
b1011 !
b1011 $
#1050084
0"
#1054251
1"
#1055251
b1001 !
b1001 $
#1058418
0"
#1062585
1"
#1063585
b1000 !
b1000 $
#1066752
0"
#1070919
1"
#1071919
b0 !
b0 $
#1075086
0"
#1079253
1"
#1080253
b1 !
b1 $
#1083420
0"
#1087587
1"
#1088587
b11 !
b11 $
#1091754
0"
#1095921
1"
#1096921
b10 !
b10 $
#1100088
0"
#1104255
1"
#1105255
b110 !
b110 $
#1108422
0"
#1112589
1"
#1113589
b111 !
b111 $
#1116756
0"
#1120923
1"
#1121923
b101 !
b101 $
#1125090
0"
#1129257
1"
#1130257
b100 !
b100 $
#1133424
0"
#1137591
1"
#1138591
b1100 !
b1100 $
#1141758
0"
#1145925
1"
#1146925
b1101 !
b1101 $
#1150092
0"
#1154259
1"
#1155259
b1111 !
b1111 $
#1158426
0"
#1162593
1"
#1163593
b1110 !
b1110 $
#1166760
0"
#1170927
1"
#1171927
b1010 !
b1010 $
#1175094
0"
#1179261
1"
#1180261
b1011 !
b1011 $
#1183428
0"
#1187595
1"
#1188595
b1001 !
b1001 $
#1191762
0"
#1195929
1"
#1196929
b1000 !
b1000 $
#1200096
0"
#1204263
1"
#1205263
b0 !
b0 $
#1208430
0"
#1212597
1"
#1213597
b1 !
b1 $
#1216764
0"
#1220931
1"
#1221931
b11 !
b11 $
#1225098
0"
#1229265
1"
#1230265
b10 !
b10 $
#1233432
0"
#1237599
1"
#1238599
b110 !
b110 $
#1241766
0"
#1245933
1"
#1246933
b111 !
b111 $
#1250100
0"
#1254267
1"
#1255267
b101 !
b101 $
#1258434
0"
#1262601
1"
#1263601
b100 !
b100 $
#1266768
0"
#1270935
1"
#1271935
b1100 !
b1100 $
#1275102
0"
#1279269
1"
#1280269
b1101 !
b1101 $
#1283436
0"
#1287603
1"
#1288603
b1111 !
b1111 $
#1291770
0"
#1295937
1"
#1296937
b1110 !
b1110 $
#1300104
0"
#1304271
1"
#1305271
b1010 !
b1010 $
#1308438
0"
#1312605
1"
#1313605
b1011 !
b1011 $
#1316772
0"
#1320939
1"
#1321939
b1001 !
b1001 $
#1325106
0"
#1329273
1"
#1330273
b1000 !
b1000 $
#1333440
0"
#1337607
1"
#1338607
b0 !
b0 $
#1341774
0"
#1345941
1"
#1346941
b1 !
b1 $
#1350108
0"
#1354275
1"
#1355275
b11 !
b11 $
#1358442
0"
#1362609
1"
#1363609
b10 !
b10 $
#1366776
0"
#1370943
1"
#1371943
b110 !
b110 $
#1375110
0"
#1379277
1"
#1380277
b111 !
b111 $
#1383444
0"
#1387611
1"
#1388611
b101 !
b101 $
#1391778
0"
#1395945
1"
#1396945
b100 !
b100 $
#1400112
0"
#1404279
1"
#1405279
b1100 !
b1100 $
#1408446
0"
#1412613
1"
#1413613
b1101 !
b1101 $
#1416780
0"
#1420947
1"
#1421947
b1111 !
b1111 $
#1425114
0"
#1429281
1"
#1430281
b1110 !
b1110 $
#1433448
0"
#1437615
1"
#1438615
b1010 !
b1010 $
#1441782
0"
#1445949
1"
#1446949
b1011 !
b1011 $
#1450116
0"
#1454283
1"
#1455283
b1001 !
b1001 $
#1458450
0"
#1462617
1"
#1463617
b1000 !
b1000 $
#1466784
0"
#1470951
1"
#1471951
b0 !
b0 $
#1475118
0"
#1479285
1"
#1480285
b1 !
b1 $
#1483452
0"
#1487619
1"
#1488619
b11 !
b11 $
#1491786
0"
#1495953
1"
#1496953
b10 !
b10 $
#1500120
0"
#1504287
1"
#1505287
b110 !
b110 $
#1508454
0"
#1512621
1"
#1513621
b111 !
b111 $
#1516788
0"
#1520955
1"
#1521955
b101 !
b101 $
#1525122
0"
#1529289
1"
#1530289
b100 !
b100 $
#1533456
0"
#1537623
1"
#1538623
b1100 !
b1100 $
#1541790
0"
#1545957
1"
#1546957
b1101 !
b1101 $
#1550124
0"
#1554291
1"
#1555291
b1111 !
b1111 $
#1558458
0"
#1562625
1"
#1563625
b1110 !
b1110 $
#1566792
0"
#1570959
1"
#1571959
b1010 !
b1010 $
#1575126
0"
#1579293
1"
#1580293
b1011 !
b1011 $
#1583460
0"
#1587627
1"
#1588627
b1001 !
b1001 $
#1591794
0"
#1595961
1"
#1596961
b1000 !
b1000 $
#1600128
0"
#1604295
1"
#1605295
b0 !
b0 $
#1608462
0"
#1612629
1"
#1613629
b1 !
b1 $
#1616796
0"
#1620963
1"
#1621963
b11 !
b11 $
#1625130
0"
#1629297
1"
#1630297
b10 !
b10 $
#1633464
0"
#1637631
1"
#1638631
b110 !
b110 $
#1641798
0"
#1645965
1"
#1646965
b111 !
b111 $
#1650132
0"
#1654299
1"
#1655299
b101 !
b101 $
#1658466
0"
#1662633
1"
#1663633
b100 !
b100 $
#1666800
0"
#1670967
1"
#1671967
b1100 !
b1100 $
#1675134
0"
#1679301
1"
#1680301
b1101 !
b1101 $
#1683468
0"
#1687635
1"
#1688635
b1111 !
b1111 $
#1691802
0"
#1695969
1"
#1696969
b1110 !
b1110 $
#1700136
0"
#1704303
1"
#1705303
b1010 !
b1010 $
#1708470
0"
#1712637
1"
#1713637
b1011 !
b1011 $
#1716804
0"
#1720971
1"
#1721971
b1001 !
b1001 $
#1725138
0"
#1729305
1"
#1730305
b1000 !
b1000 $
#1733472
0"
#1737639
1"
#1738639
b0 !
b0 $
#1741806
0"
#1745973
1"
#1746973
b1 !
b1 $
#1750140
0"
#1754307
1"
#1755307
b11 !
b11 $
#1758474
0"
#1762641
1"
#1763641
b10 !
b10 $
#1766808
0"
#1770975
1"
#1771975
b110 !
b110 $
#1775142
0"
#1779309
1"
#1780309
b111 !
b111 $
#1783476
0"
#1787643
1"
#1788643
b101 !
b101 $
#1791810
0"
#1795977
1"
#1796977
b100 !
b100 $
#1800144
0"
#1804311
1"
#1805311
b1100 !
b1100 $
#1808478
0"
#1812645
1"
#1813645
b1101 !
b1101 $
#1816812
0"
#1820979
1"
#1821979
b1111 !
b1111 $
#1825146
0"
#1829313
1"
#1830313
b1110 !
b1110 $
#1833480
0"
#1837647
1"
#1838647
b1010 !
b1010 $
#1841814
0"
#1845981
1"
#1846981
b1011 !
b1011 $
#1850148
0"
#1854315
1"
#1855315
b1001 !
b1001 $
#1858482
0"
#1862649
1"
#1863649
b1000 !
b1000 $
#1866816
0"
#1870983
1"
#1871983
b0 !
b0 $
#1875150
0"
#1879317
1"
#1880317
b1 !
b1 $
#1883484
0"
#1887651
1"
#1888651
b11 !
b11 $
#1891818
0"
#1895985
1"
#1896985
b10 !
b10 $
#1900152
0"
#1904319
1"
#1905319
b110 !
b110 $
#1908486
0"
#1912653
1"
#1913653
b111 !
b111 $
#1916820
0"
#1920987
1"
#1921987
b101 !
b101 $
#1925154
0"
#1929321
1"
#1930321
b100 !
b100 $
#1933488
0"
#1937655
1"
#1938655
b1100 !
b1100 $
#1941822
0"
#1945989
1"
#1946989
b1101 !
b1101 $
#1950156
0"
#1954323
1"
#1955323
b1111 !
b1111 $
#1958490
0"
#1962657
1"
#1963657
b1110 !
b1110 $
#1966824
0"
#1970991
1"
#1971991
b1010 !
b1010 $
#1975158
0"
#1979325
1"
#1980325
b1011 !
b1011 $
#1983492
0"
#1987659
1"
#1988659
b1001 !
b1001 $
#1991826
0"
#1995993
1"
#1996993
b1000 !
b1000 $
#2000160
0"
#2004327
1"
#2005327
b0 !
b0 $
#2008494
0"
#2012661
1"
#2013661
b1 !
b1 $
#2016828
0"
#2020995
1"
#2021995
b11 !
b11 $
#2025162
0"
#2029329
1"
#2030329
b10 !
b10 $
#2033496
0"
#2037663
1"
#2038663
b110 !
b110 $
#2041830
0"
#2045997
1"
#2046997
b111 !
b111 $
#2050164
0"
#2054331
1"
#2055331
b101 !
b101 $
#2058498
0"
#2062665
1"
#2063665
b100 !
b100 $
#2066832
0"
#2070999
1"
#2071999
b1100 !
b1100 $
#2075166
0"
#2079333
1"
#2080333
b1101 !
b1101 $
#2083500
0"
#2087667
1"
#2088667
b1111 !
b1111 $
#2091834
0"
#2096001
1"
#2097001
b1110 !
b1110 $
#2100168
0"
#2104335
1"
#2105335
b1010 !
b1010 $
#2108502
0"
#2112669
1"
#2113669
b1011 !
b1011 $
#2116836
0"
#2121003
1"
#2122003
b1001 !
b1001 $
#2125170
0"
#2129337
1"
#2130337
b1000 !
b1000 $
#2133504
0"
#2137671
1"
#2138671
b0 !
b0 $
#2141838
0"
#2146005
1"
#2147005
b1 !
b1 $
#2150172
0"
#2154339
1"
#2155339
b11 !
b11 $
#2158506
0"
#2162673
1"
#2163673
b10 !
b10 $
#2166840
0"
#2171007
1"
#2172007
b110 !
b110 $
#2175174
0"
#2179341
1"
#2180341
b111 !
b111 $
#2183508
0"
#2187675
1"
#2188675
b101 !
b101 $
#2191842
0"
#2196009
1"
#2197009
b100 !
b100 $
#2200176
0"
#2204343
1"
#2205343
b1100 !
b1100 $
#2208510
0"
#2212677
1"
#2213677
b1101 !
b1101 $
#2216844
0"
#2221011
1"
#2222011
b1111 !
b1111 $
#2225178
0"
#2229345
1"
#2230345
b1110 !
b1110 $
#2233512
0"
#2237679
1"
#2238679
b1010 !
b1010 $
#2241846
0"
#2246013
1"
#2247013
b1011 !
b1011 $
#2250180
0"
#2254347
1"
#2255347
b1001 !
b1001 $
#2258514
0"
#2262681
1"
#2263681
b1000 !
b1000 $
#2266848
0"
#2271015
1"
#2272015
b0 !
b0 $
#2275182
0"
#2279349
1"
#2280349
b1 !
b1 $
#2283516
0"
#2287683
1"
#2288683
b11 !
b11 $
#2291850
0"
#2296017
1"
#2297017
b10 !
b10 $
#2300184
0"
#2304351
1"
#2305351
b110 !
b110 $
#2308518
0"
#2312685
1"
#2313685
b111 !
b111 $
#2316852
0"
#2321019
1"
#2322019
b101 !
b101 $
#2325186
0"
#2329353
1"
#2330353
b100 !
b100 $
#2333520
0"
#2337687
1"
#2338687
b1100 !
b1100 $
#2341854
0"
#2346021
1"
#2347021
b1101 !
b1101 $
#2350188
0"
#2354355
1"
#2355355
b1111 !
b1111 $
#2358522
0"
#2362689
1"
#2363689
b1110 !
b1110 $
#2366856
0"
#2371023
1"
#2372023
b1010 !
b1010 $
#2375190
0"
#2379357
1"
#2380357
b1011 !
b1011 $
#2383524
0"
#2387691
1"
#2388691
b1001 !
b1001 $
#2391858
0"
#2396025
1"
#2397025
b1000 !
b1000 $
#2400192
0"
#2404359
1"
#2405359
b0 !
b0 $
#2408526
0"
#2412693
1"
#2413693
b1 !
b1 $
#2416860
0"
#2421027
1"
#2422027
b11 !
b11 $
#2425194
0"
#2429361
1"
#2430361
b10 !
b10 $
#2433528
0"
#2437695
1"
#2438695
b110 !
b110 $
#2441862
0"
#2446029
1"
#2447029
b111 !
b111 $
#2450196
0"
#2454363
1"
#2455363
b101 !
b101 $
#2458530
0"
#2462697
1"
#2463697
b100 !
b100 $
#2466864
0"
#2471031
1"
#2472031
b1100 !
b1100 $
#2475198
0"
#2479365
1"
#2480365
b1101 !
b1101 $
#2483532
0"
#2487699
1"
#2488699
b1111 !
b1111 $
#2491866
0"
#2496033
1"
#2497033
b1110 !
b1110 $
#2500200
0"
#2504367
1"
#2505367
b1010 !
b1010 $
#2508534
0"
#2512701
1"
#2513701
b1011 !
b1011 $
#2516868
0"
#2521035
1"
#2522035
b1001 !
b1001 $
#2525202
0"
#2529369
1"
#2530369
b1000 !
b1000 $
#2533536
0"
#2537703
1"
#2538703
b0 !
b0 $
#2541870
0"
#2546037
1"
#2547037
b1 !
b1 $
#2550204
0"
#2554371
1"
#2555371
b11 !
b11 $
#2558538
0"
#2562705
1"
#2563705
b10 !
b10 $
#2566872
0"
#2571039
1"
#2572039
b110 !
b110 $
#2575206
0"
#2579373
1"
#2580373
b111 !
b111 $
#2583540
0"
#2587707
1"
#2588707
b101 !
b101 $
#2591874
0"
#2596041
1"
#2597041
b100 !
b100 $
#2600208
0"
#2604375
1"
#2605375
b1100 !
b1100 $
#2608542
0"
#2612709
1"
#2613709
b1101 !
b1101 $
#2616876
0"
#2621043
1"
#2622043
b1111 !
b1111 $
#2625210
0"
#2629377
1"
#2630377
b1110 !
b1110 $
#2633544
0"
#2637711
1"
#2638711
b1010 !
b1010 $
#2641878
0"
#2646045
1"
#2647045
b1011 !
b1011 $
#2650212
0"
#2654379
1"
#2655379
b1001 !
b1001 $
#2658546
0"
#2662713
1"
#2663713
b1000 !
b1000 $
#2666880
0"
#2671047
1"
#2672047
b0 !
b0 $
#2675214
0"
#2679381
1"
#2680381
b1 !
b1 $
#2683548
0"
#2687715
1"
#2688715
b11 !
b11 $
#2691882
0"
#2696049
1"
#2697049
b10 !
b10 $
#2700216
0"
#2704383
1"
#2705383
b110 !
b110 $
#2708550
0"
#2712717
1"
#2713717
b111 !
b111 $
#2716884
0"
#2721051
1"
#2722051
b101 !
b101 $
#2725218
0"
#2729385
1"
#2730385
b100 !
b100 $
#2733552
0"
#2737719
1"
#2738719
b1100 !
b1100 $
#2741886
0"
#2746053
1"
#2747053
b1101 !
b1101 $
#2750220
0"
#2754387
1"
#2755387
b1111 !
b1111 $
#2758554
0"
#2762721
1"
#2763721
b1110 !
b1110 $
#2766888
0"
#2771055
1"
#2772055
b1010 !
b1010 $
#2775222
0"
#2779389
1"
#2780389
b1011 !
b1011 $
#2783556
0"
#2787723
1"
#2788723
b1001 !
b1001 $
#2791890
0"
#2796057
1"
#2797057
b1000 !
b1000 $
#2800224
0"
#2804391
1"
#2805391
b0 !
b0 $
#2808558
0"
#2812725
1"
#2813725
b1 !
b1 $
#2816892
0"
#2821059
1"
#2822059
b11 !
b11 $
#2825226
0"
#2829393
1"
#2830393
b10 !
b10 $
#2833560
0"
#2837727
1"
#2838727
b110 !
b110 $
#2841894
0"
#2846061
1"
#2847061
b111 !
b111 $
#2850228
0"
#2854395
1"
#2855395
b101 !
b101 $
#2858562
0"
#2862729
1"
#2863729
b100 !
b100 $
#2866896
0"
#2871063
1"
#2872063
b1100 !
b1100 $
#2875230
0"
#2879397
1"
#2880397
b1101 !
b1101 $
#2883564
0"
#2887731
1"
#2888731
b1111 !
b1111 $
#2891898
0"
#2896065
1"
#2897065
b1110 !
b1110 $
#2900232
0"
#2904399
1"
#2905399
b1010 !
b1010 $
#2908566
0"
#2912733
1"
#2913733
b1011 !
b1011 $
#2916900
0"
#2921067
1"
#2922067
b1001 !
b1001 $
#2925234
0"
#2929401
1"
#2930401
b1000 !
b1000 $
#2933568
0"
#2937735
1"
#2938735
b0 !
b0 $
#2941902
0"
#2946069
1"
#2947069
b1 !
b1 $
#2950236
0"
#2954403
1"
#2955403
b11 !
b11 $
#2958570
0"
#2962737
1"
#2963737
b10 !
b10 $
#2966904
0"
#2971071
1"
#2972071
b110 !
b110 $
#2975238
0"
#2979405
1"
#2980405
b111 !
b111 $
#2983572
0"
#2987739
1"
#2988739
b101 !
b101 $
#2991906
0"
#2996073
1"
#2997073
b100 !
b100 $
#3000240
0"
#3004407
1"
#3005407
b1100 !
b1100 $
#3008574
0"
#3012741
1"
#3013741
b1101 !
b1101 $
#3016908
0"
#3021075
1"
#3022075
b1111 !
b1111 $
#3025242
0"
#3029409
1"
#3030409
b1110 !
b1110 $
#3033576
0"
#3037743
1"
#3038743
b1010 !
b1010 $
#3041910
0"
#3046077
1"
#3047077
b1011 !
b1011 $
#3050244
0"
#3054411
1"
#3055411
b1001 !
b1001 $
#3058578
0"
#3062745
1"
#3063745
b1000 !
b1000 $
#3066912
0"
#3071079
1"
#3072079
b0 !
b0 $
#3075246
0"
#3079413
1"
#3080413
b1 !
b1 $
#3083580
0"
#3087747
1"
#3088747
b11 !
b11 $
#3091914
0"
#3096081
1"
#3097081
b10 !
b10 $
#3100248
0"
#3104415
1"
#3105415
b110 !
b110 $
#3108582
0"
#3112749
1"
#3113749
b111 !
b111 $
#3116916
0"
#3121083
1"
#3122083
b101 !
b101 $
#3125250
0"
#3129417
1"
#3130417
b100 !
b100 $
#3133584
0"
#3137751
1"
#3138751
b1100 !
b1100 $
#3141918
0"
#3146085
1"
#3147085
b1101 !
b1101 $
#3150252
0"
#3154419
1"
#3155419
b1111 !
b1111 $
#3158586
0"
#3162753
1"
#3163753
b1110 !
b1110 $
#3166920
0"
#3171087
1"
#3172087
b1010 !
b1010 $
#3175254
0"
#3179421
1"
#3180421
b1011 !
b1011 $
#3183588
0"
#3187755
1"
#3188755
b1001 !
b1001 $
#3191922
0"
#3196089
1"
#3197089
b1000 !
b1000 $
#3200256
0"
#3204423
1"
#3205423
b0 !
b0 $
#3208590
0"
#3212757
1"
#3213757
b1 !
b1 $
#3216924
0"
#3221091
1"
#3222091
b11 !
b11 $
#3225258
0"
#3229425
1"
#3230425
b10 !
b10 $
#3233592
0"
#3237759
1"
#3238759
b110 !
b110 $
#3241926
0"
#3246093
1"
#3247093
b111 !
b111 $
#3250260
0"
#3254427
1"
#3255427
b101 !
b101 $
#3258594
0"
#3262761
1"
#3263761
b100 !
b100 $
#3266928
0"
#3271095
1"
#3272095
b1100 !
b1100 $
#3275262
0"
#3279429
1"
#3280429
b1101 !
b1101 $
#3283596
0"
#3287763
1"
#3288763
b1111 !
b1111 $
#3291930
0"
#3296097
1"
#3297097
b1110 !
b1110 $
#3300264
0"
#3304431
1"
#3305431
b1010 !
b1010 $
#3308598
0"
#3312765
1"
#3313765
b1011 !
b1011 $
#3316932
0"
#3321099
1"
#3322099
b1001 !
b1001 $
#3325266
0"
#3329433
1"
#3330433
b1000 !
b1000 $
#3333600
0"
#3337767
1"
#3338767
b0 !
b0 $
#3341934
0"
#3346101
1"
#3347101
b1 !
b1 $
#3350268
0"
#3354435
1"
#3355435
b11 !
b11 $
#3358602
0"
#3362769
1"
#3363769
b10 !
b10 $
#3366936
0"
#3371103
1"
#3372103
b110 !
b110 $
#3375270
0"
#3379437
1"
#3380437
b111 !
b111 $
#3383604
0"
#3387771
1"
#3388771
b101 !
b101 $
#3391938
0"
#3396105
1"
#3397105
b100 !
b100 $
#3400272
0"
#3404439
1"
#3405439
b1100 !
b1100 $
#3408606
0"
#3412773
1"
#3413773
b1101 !
b1101 $
#3416940
0"
#3421107
1"
#3422107
b1111 !
b1111 $
#3425274
0"
#3429441
1"
#3430441
b1110 !
b1110 $
#3433608
0"
#3437775
1"
#3438775
b1010 !
b1010 $
#3441942
0"
#3446109
1"
#3447109
b1011 !
b1011 $
#3450276
0"
#3454443
1"
#3455443
b1001 !
b1001 $
#3458610
0"
#3462777
1"
#3463777
b1000 !
b1000 $
#3466944
0"
#3471111
1"
#3472111
b0 !
b0 $
#3475278
0"
#3479445
1"
#3480445
b1 !
b1 $
#3483612
0"
#3487779
1"
#3488779
b11 !
b11 $
#3491946
0"
#3496113
1"
#3497113
b10 !
b10 $
#3500280
0"
#3504447
1"
#3505447
b110 !
b110 $
#3508614
0"
#3512781
1"
#3513781
b111 !
b111 $
#3516948
0"
#3521115
1"
#3522115
b101 !
b101 $
#3525282
0"
#3529449
1"
#3530449
b100 !
b100 $
#3533616
0"
#3537783
1"
#3538783
b1100 !
b1100 $
#3541950
0"
#3546117
1"
#3547117
b1101 !
b1101 $
#3550284
0"
#3554451
1"
#3555451
b1111 !
b1111 $
#3558618
0"
#3562785
1"
#3563785
b1110 !
b1110 $
#3566952
0"
#3571119
1"
#3572119
b1010 !
b1010 $
#3575286
0"
#3579453
1"
#3580453
b1011 !
b1011 $
#3583620
0"
#3587787
1"
#3588787
b1001 !
b1001 $
#3591954
0"
#3596121
1"
#3597121
b1000 !
b1000 $
#3600288
0"
#3604455
1"
#3605455
b0 !
b0 $
#3608622
0"
#3612789
1"
#3613789
b1 !
b1 $
#3616956
0"
#3621123
1"
#3622123
b11 !
b11 $
#3625290
0"
#3629457
1"
#3630457
b10 !
b10 $
#3633624
0"
#3637791
1"
#3638791
b110 !
b110 $
#3641958
0"
#3646125
1"
#3647125
b111 !
b111 $
#3650292
0"
#3654459
1"
#3655459
b101 !
b101 $
#3658626
0"
#3662793
1"
#3663793
b100 !
b100 $
#3666960
0"
#3671127
1"
#3672127
b1100 !
b1100 $
#3675294
0"
#3679461
1"
#3680461
b1101 !
b1101 $
#3683628
0"
#3687795
1"
#3688795
b1111 !
b1111 $
#3691962
0"
#3696129
1"
#3697129
b1110 !
b1110 $
#3700296
0"
#3704463
1"
#3705463
b1010 !
b1010 $
#3708630
0"
#3712797
1"
#3713797
b1011 !
b1011 $
